nonebot_plugin_apscheduler/__init__.py
nonebot_plugin_apscheduler/config.py
nonebot_plugin_apscheduler-0.4.0.dist-info/LICENSE
nonebot_plugin_apscheduler-0.4.0.dist-info/METADATA
nonebot_plugin_apscheduler-0.4.0.dist-info/WHEEL
nonebot_plugin_apscheduler-0.4.0.dist-info/RECORD
