Metadata-Version: 2.1
Name: nonebot-plugin-apscheduler
Version: 0.4.0
Summary: APScheduler Support for NoneBot2
Home-page: https://github.com/nonebot/plugin-apscheduler
License: MIT
Author: yanyongyu
Author-email: yyy@nonebot.dev
Requires-Python: >=3.8,<4.0
Classifier: License :: OSI Approved :: MIT License
Classifier: Programming Language :: Python :: 3
Classifier: Programming Language :: Python :: 3.8
Classifier: Programming Language :: Python :: 3.9
Classifier: Programming Language :: Python :: 3.10
Classifier: Programming Language :: Python :: 3.11
Classifier: Programming Language :: Python :: 3.12
Requires-Dist: apscheduler (>=3.7.0,<4.0.0)
Requires-Dist: nonebot2 (>=2.2.0,<3.0.0)
Requires-Dist: pydantic (>=1.10.0,<3.0.0,!=2.5.0,!=2.5.1)
Project-URL: Documentation, https://github.com/nonebot/plugin-apscheduler#readme
Project-URL: Repository, https://github.com/nonebot/plugin-apscheduler
